mips cpu/exp.1-2.v
`timescale 1 ns/1 ps
module andgates(
    input wire a,
    input wire b,
    output wire out
);
  assign out = a&b;
endmodule // 

module orgates(
    input wire a,
    input wire b,
    output wire out
);
  assign out = a|b;
endmodule //


module notandgates(
    input wire a,
    input wire b,
    output wire out
);
  assign out = ~(a&b);
endmodule //

module notorgates(
    input wire a,
    input wire b,
    output wire out
);
  assign out = ~(a|b);
endmodule //

module notgates(
    input wire a,
    output wire out
);
  assign out = ~a;
endmodule // notgatesinput wire a,

module gate(a,b,c,d,out);
  input a,b,c,d;
  output out;
  wire a,b,c,d,out;
  wire a_,b_,c_,d_;
  orgates g1(a,b,a_);
  notgates g2(b,b_);
  notorgates g3(c,d,c_);
  notandgates g4(b_,c_,d_);
  andgates g5(a_,d_,out);
endmodule // testfiture

module exp1_td;
  reg a,b,c,d;
  wire out;

  gate damo(a,b,c,d,out);

  always @(posedge a) begin
    c = ~c;
    d = ~d;
  end
  initial begin

    $dumpfile("exp1.vcd");
    $dumpvars(0,exp1_td);
    a = 1;
    b = 1;
    c = 0;
    d = 1;
    repeat(100)begin
      #5 a = ~a;
      #5 b = ~b;
    end
  end
endmodule

mips cpu/exp1.vcd
$date
	Wed Sep 25 15:30:43 2019
$end
$version
	Icarus Verilog
$end
$timescale
	1ps
$end
$scope module exp1_td $end
$var wire 1 ! out $end
$var reg 1 " a $end
$var reg 1 # b $end
$var reg 1 $ c $end
$var reg 1 % d $end
$scope module damo $end
$var wire 1 " a $end
$var wire 1 # b $end
$var wire 1 $ c $end
$var wire 1 % d $end
$var wire 1 ! out $end
$var wire 1 & d_ $end
$var wire 1 ' c_ $end
$var wire 1 ( b_ $end
$var wire 1 ) a_ $end
$scope module g1 $end
$var wire 1 " a $end
$var wire 1 # b $end
$var wire 1 ) out $end
$upscope $end
$scope module g2 $end
$var wire 1 # a $end
$var wire 1 ( out $end
$upscope $end
$scope module g3 $end
$var wire 1 $ a $end
$var wire 1 % b $end
$var wire 1 ' out $end
$upscope $end
$scope module g4 $end
$var wire 1 ( a $end
$var wire 1 ' b $end
$var wire 1 & out $end
$upscope $end
$scope module g5 $end
$var wire 1 ) a $end
$var wire 1 & b $end
$var wire 1 ! out $end
$upscope $end
$upscope $end
$upscope $end
$enddefinitions $end
#0
$dumpvars
1)
0(
0'
1&
0%
1$
1#
1"
1!
$end
#5000
0"
#10000
0!
0)
1(
0#
#15000
1!
1)
1%
0$
1"
#20000
0(
1#
#25000
0"
#30000
0!
0)
1(
0#
#35000
1!
1)
0%
1$
1"
#40000
0(
1#
#45000
0"
#50000
0!
0)
1(
0#
#55000
1!
1)
1%
0$
1"
#60000
0(
1#
#65000
0"
#70000
0!
0)
1(
0#
#75000
1!
1)
0%
1$
1"
#80000
0(
1#
#85000
0"
#90000
0!
0)
1(
0#
#95000
1!
1)
1%
0$
1"
#100000
0(
1#
#105000
0"
#110000
0!
0)
1(
0#
#115000
1!
1)
0%
1$
1"
#120000
0(
1#
#125000
0"
#130000
0!
0)
1(
0#
#135000
1!
1)
1%
0$
1"
#140000
0(
1#
#145000
0"
#150000
0!
0)
1(
0#
#155000
1!
1)
0%
1$
1"
#160000
0(
1#
#165000
0"
#170000
0!
0)
1(
0#
#175000
1!
1)
1%
0$
1"
#180000
0(
1#
#185000
0"
#190000
0!
0)
1(
0#
#195000
1!
1)
0%
1$
1"
#200000
0(
1#
#205000
0"
#210000
0!
0)
1(
0#
#215000
1!
1)
1%
0$
1"
#220000
0(
1#
#225000
0"
#230000
0!
0)
1(
0#
#235000
1!
1)
0%
1$
1"
#240000
0(
1#
#245000
0"
#250000
0!
0)
1(
0#
#255000
1!
1)
1%
0$
1"
#260000
0(
1#
#265000
0"
#270000
0!
0)
1(
0#
#275000
1!
1)
0%
1$
1"
#280000
0(
1#
#285000
0"
#290000
0!
0)
1(
0#
#295000
1!
1)
1%
0$
1"
#300000
0(
1#
#305000
0"
#310000
0!
0)
1(
0#
#315000
1!
1)
0%
1$
1"
#320000
0(
1#
#325000
0"
#330000
0!
0)
1(
0#
#335000
1!
1)
1%
0$
1"
#340000
0(
1#
#345000
0"
#350000
0!
0)
1(
0#
#355000
1!
1)
0%
1$
1"
#360000
0(
1#
#365000
0"
#370000
0!
0)
1(
0#
#375000
1!
1)
1%
0$
1"
#380000
0(
1#
#385000
0"
#390000
0!
0)
1(
0#
#395000
1!
1)
0%
1$
1"
#400000
0(
1#
#405000
0"
#410000
0!
0)
1(
0#
#415000
1!
1)
1%
0$
1"
#420000
0(
1#
#425000
0"
#430000
0!
0)
1(
0#
#435000
1!
1)
0%
1$
1"
#440000
0(
1#
#445000
0"
#450000
0!
0)
1(
0#
#455000
1!
1)
1%
0$
1"
#460000
0(
1#
#465000
0"
#470000
0!
0)
1(
0#
#475000
1!
1)
0%
1$
1"
#480000
0(
1#
#485000
0"
#490000
0!
0)
1(
0#
#495000
1!
1)
1%
0$
1"
#500000
0(
1#
#505000
0"
#510000
0!
0)
1(
0#
#515000
1!
1)
0%
1$
1"
#520000
0(
1#
#525000
0"
#530000
0!
0)
1(
0#
#535000
1!
1)
1%
0$
1"
#540000
0(
1#
#545000
0"
#550000
0!
0)
1(
0#
#555000
1!
1)
0%
1$
1"
#560000
0(
1#
#565000
0"
#570000
0!
0)
1(
0#
#575000
1!
1)
1%
0$
1"
#580000
0(
1#
#585000
0"
#590000
0!
0)
1(
0#
#595000
1!
1)
0%
1$
1"
#600000
0(
1#
#605000
0"
#610000
0!
0)
1(
0#
#615000
1!
1)
1%
0$
1"
#620000
0(
1#
#625000
0"
#630000
0!
0)
1(
0#
#635000
1!
1)
0%
1$
1"
#640000
0(
1#
#645000
0"
#650000
0!
0)
1(
0#
#655000
1!
1)
1%
0$
1"
#660000
0(
1#
#665000
0"
#670000
0!
0)
1(
0#
#675000
1!
1)
0%
1$
1"
#680000
0(
1#
#685000
0"
#690000
0!
0)
1(
0#
#695000
1!
1)
1%
0$
1"
#700000
0(
1#
#705000
0"
#710000
0!
0)
1(
0#
#715000
1!
1)
0%
1$
1"
#720000
0(
1#
#725000
0"
#730000
0!
0)
1(
0#
#735000
1!
1)
1%
0$
1"
#740000
0(
1#
#745000
0"
#750000
0!
0)
1(
0#
#755000
1!
1)
0%
1$
1"
#760000
0(
1#
#765000
0"
#770000
0!
0)
1(
0#
#775000
1!
1)
1%
0$
1"
#780000
0(
1#
#785000
0"
#790000
0!
0)
1(
0#
#795000
1!
1)
0%
1$
1"
#800000
0(
1#
#805000
0"
#810000
0!
0)
1(
0#
#815000
1!
1)
1%
0$
1"
#820000
0(
1#
#825000
0"
#830000
0!
0)
1(
0#
#835000
1!
1)
0%
1$
1"
#840000
0(
1#
#845000
0"
#850000
0!
0)
1(
0#
#855000
1!
1)
1%
0$
1"
#860000
0(
1#
#865000
0"
#870000
0!
0)
1(
0#
#875000
1!
1)
0%
1$
1"
#880000
0(
1#
#885000
0"
#890000
0!
0)
1(
0#
#895000
1!
1)
1%
0$
1"
#900000
0(
1#
#905000
0"
#910000
0!
0)
1(
0#
#915000
1!
1)
0%
1$
1"
#920000
0(
1#
#925000
0"
#930000
0!
0)
1(
0#
#935000
1!
1)
1%
0$
1"
#940000
0(
1#
#945000
0"
#950000
0!
0)
1(
0#
#955000
1!
1)
0%
1$
1"
#960000
0(
1#
#965000
0"
#970000
0!
0)
1(
0#
#975000
1!
1)
1%
0$
1"
#980000
0(
1#
#985000
0"
#990000
0!
0)
1(
0#
#995000
1!
1)
0%
1$
1"
#1000000
0(
1#
