mips cpu/exp-6.v
`timescale 1 ns/1 ps
module counter(
    input clk,
    input a,
    output reg sign
);
reg count = 0;
reg [2:0]s;
always @(posedge clk)begin
  s={s[1:0],a};
  if(s == 3'b101)begin
    count = count +1;
    sign = 1;
  end else begin
    sign =0;
  end
end
endmodule //

module exp6_td;
    reg a,clk;
    wire sidn;
    counter t(clk,a,sign);
    initial begin
      clk <= 0;
      repeat(100)begin
        #5 clk = ~clk; 
      end
    end
    initial begin
      $dumpfile("exp6_td.vcd");
      $dumpvars(0,exp6_td);
      a = 0;
      #20 a = 1;
      #10 a = 0;
      #10 a = 1;
      #30 a = 0;
      #10 a = 1;
    end

endmodule //

mips cpu/exp6_td.vcd
$date
	Tue Oct 22 17:02:39 2019
$end
$version
	Icarus Verilog
$end
$timescale
	1ps
$end
$scope module exp6_td $end
$var wire 1 ! sign $end
$var reg 1 " a $end
$var reg 1 # clk $end
$scope module t $end
$var wire 1 " a $end
$var wire 1 # clk $end
$var reg 1 $ count $end
$var reg 3 % s [2:0] $end
$var reg 1 ! sign $end
$upscope $end
$upscope $end
$enddefinitions $end
#0
$dumpvars
bx %
0$
0#
0"
x!
$end
#5000
0!
bx0 %
1#
#10000
0#
#15000
bx00 %
1#
#20000
0#
1"
#25000
b1 %
1#
#30000
0#
0"
#35000
b10 %
1#
#40000
0#
1"
#45000
1!
1$
b101 %
1#
#50000
0#
#55000
0!
b11 %
1#
#60000
0#
#65000
b111 %
1#
#70000
0#
0"
#75000
b110 %
1#
#80000
0#
1"
#85000
1!
0$
b101 %
1#
#90000
0#
#95000
0!
b11 %
1#
#100000
0#
#105000
b111 %
1#
