mips cpu/exp8.v
module ALU(
    input clk,
    input signed[15:0] alu_in1,
    input signed[15:0] alu_in2,
    input [3:0]operations,
    output reg[15:0] alu_out_16,
    output reg[31:0] alu_out
);
parameter NOP = 4'b0000;
parameter ADD = 4'b0001;
parameter SUB = 4'b0010;
parameter MUL = 4'b0011;
parameter DIV = 4'b0100;
parameter AND = 4'b0101;
parameter OR = 4'b0110;
parameter NOR = 4'b0111;
parameter XOR = 4'b1000;
parameter ROR = 4'b1001;
parameter ROL = 4'b1010;

always @(posedge clk) begin
    case(operations)
        NOP:alu_out_16<=32'h0;
        ADD:alu_out_16<=alu_in1+alu_in2;
        SUB:alu_out_16<=alu_in1-alu_in2;
        MUL:alu_out<=alu_in1*alu_in2;
        DIV:alu_out_16<=alu_in1/alu_in2;
        AND:alu_out_16<=alu_in1&alu_in2;
        OR:alu_out_16<=alu_in1|alu_in2;
        NOR:alu_out_16<=alu_in1~^alu_in2;
        XOR:alu_out_16<=alu_in1^alu_in2;
        ROR:alu_out_16<={alu_in1[0],alu_in1[15:1]};
        ROL:alu_out_16<={alu_in1[14:0],alu_in1[15]};

    endcase
end
endmodule

module exp8_td;
    reg clk;
    reg[15:0]a;
    reg[15:0]b;
    wire[15:0]result1;
    wire[31:0]result2;
    reg[3:0]o;
    ALU test(clk,a,b,o,result1,result2);
    initial begin
        clk = 0;
        repeat(5000)begin
            #1 clk =~clk;
        end
    end
    initial begin
        $dumpfile("exp8_td.vcd");
        $dumpvars(0,exp8_td);
        a = 16'h1234;
        b = 16'h356a;
        o = 4'b0000;
        repeat(10)begin
            #10 o<=o+4'b0001;
        end
    end 
endmodule //

mips cpu/exp8_td.vcd
$date
	Wed Nov 06 22:13:07 2019
$end
$version
	Icarus Verilog
$end
$timescale
	1s
$end
$scope module exp8_td $end
$var wire 32 ! result2 [31:0] $end
$var wire 16 " result1 [15:0] $end
$var reg 16 # a [15:0] $end
$var reg 16 $ b [15:0] $end
$var reg 1 % clk $end
$var reg 4 & o [3:0] $end
$scope module test $end
$var wire 16 ' alu_in1 [15:0] $end
$var wire 16 ( alu_in2 [15:0] $end
$var wire 1 % clk $end
$var wire 4 ) operations [3:0] $end
$var reg 32 * alu_out [31:0] $end
$var reg 16 + alu_out_16 [15:0] $end
$upscope $end
$upscope $end
$enddefinitions $end
#0
$dumpvars
bx +
bx *
b0 )
b11010101101010 (
b1001000110100 '
b0 &
0%
b11010101101010 $
b1001000110100 #
bx "
bx !
$end
#1
b0 "
b0 +
1%
#2
0%
#3
1%
#4
0%
#5
1%
#6
0%
#7
1%
#8
0%
#9
1%
#10
b1 &
b1 )
0%
#11
b100011110011110 "
b100011110011110 +
1%
#12
0%
#13
1%
#14
0%
#15
1%
#16
0%
#17
1%
#18
0%
#19
1%
#20
b10 &
b10 )
0%
#21
b1101110011001010 "
b1101110011001010 +
1%
#22
0%
#23
1%
#24
0%
#25
1%
#26
0%
#27
1%
#28
0%
#29
1%
#30
b11 &
b11 )
0%
#31
b11110011000100110110001000 !
b11110011000100110110001000 *
1%
#32
0%
#33
1%
#34
0%
#35
1%
#36
0%
#37
1%
#38
0%
#39
1%
#40
b100 &
b100 )
0%
#41
b0 "
b0 +
1%
#42
0%
#43
1%
#44
0%
#45
1%
#46
0%
#47
1%
#48
0%
#49
1%
#50
b101 &
b101 )
0%
#51
b1000000100000 "
b1000000100000 +
1%
#52
0%
#53
1%
#54
0%
#55
1%
#56
0%
#57
1%
#58
0%
#59
1%
#60
b110 &
b110 )
0%
#61
b11011101111110 "
b11011101111110 +
1%
#62
0%
#63
1%
#64
0%
#65
1%
#66
0%
#67
1%
#68
0%
#69
1%
#70
b111 &
b111 )
0%
#71
b1101100010100001 "
b1101100010100001 +
1%
#72
0%
#73
1%
#74
0%
#75
1%
#76
0%
#77
1%
#78
0%
#79
1%
#80
b1000 &
b1000 )
0%
#81
b10011101011110 "
b10011101011110 +
1%
#82
0%
#83
1%
#84
0%
#85
1%
#86
0%
#87
1%
#88
0%
#89
1%
#90
b1001 &
b1001 )
0%
#91
b100100011010 "
b100100011010 +
1%
#92
0%
#93
1%
#94
0%
#95
1%
#96
0%
#97
1%
#98
0%
#99
1%
#100
b1010 &
b1010 )
0%
#101
b10010001101000 "
b10010001101000 +
1%
